pynative/__init__.py
pynative/pynative.py
pynative-0.0.3.dist-info/LICENSE
pynative-0.0.3.dist-info/METADATA
pynative-0.0.3.dist-info/WHEEL
pynative-0.0.3.dist-info/entry_points.txt
pynative-0.0.3.dist-info/top_level.txt
pynative-0.0.3.dist-info/RECORD
